combinatorlite/__init__.py
combinatorlite/environment/__init__.py
combinatorlite/environment/apienv.py
combinatorlite/environment/env.py
combinatorlite/interpreter/__init__.py
combinatorlite/interpreter/globalobjects.py
combinatorlite/interpreter/interpreter.py
combinatorlite/interpreter/makegraph.py
combinatorlite/interpreter/program_expression.py
combinatorlite/interpreter/type_check.py
combinatorlite-2.0.dist-info/LICENSE
combinatorlite-2.0.dist-info/METADATA
combinatorlite-2.0.dist-info/WHEEL
combinatorlite-2.0.dist-info/top_level.txt
combinatorlite-2.0.dist-info/RECORD
