Metadata-Version: 2.1
Name: combinatorlite
Version: 2.0
Summary: The programming model to integrate AI components
Home-page: https://github.com/swarna-kpaul/combinatorlite
Author: Swarna Kamal Paul
Author-email: swarna.kpaul@gmail.com
Project-URL: Bug Tracker, https://github.com/swarna-kpaul/combinatorlite/issues
Keywords: programming model,dataflow graph,functional programming,Integrative AI
Classifier: Programming Language :: Python :: 3
Classifier: License :: OSI Approved :: MIT License
Classifier: Operating System :: OS Independent
Requires-Python: >=3.6
License-File: LICENSE
Requires-Dist: requests
